mylint/__init__.py
mylint/__main__.py
mylint-0.1.0.dist-info/LICENSE
mylint-0.1.0.dist-info/METADATA
mylint-0.1.0.dist-info/WHEEL
mylint-0.1.0.dist-info/entry_points.txt
mylint-0.1.0.dist-info/top_level.txt
mylint-0.1.0.dist-info/RECORD
